skycam/__init__.py
skycam/_version.py
skycam/py.typed
skycam/adapters/__init__.py
skycam/adapters/calibration.py
skycam/adapters/image_io.py
skycam/config/__init__.py
skycam/config/settings.py
skycam/core/__init__.py
skycam/domain/__init__.py
skycam/domain/exceptions.py
skycam/domain/interpolation.py
skycam/domain/models.py
skycam/domain/projection.py
skycam/utils/__init__.py
skycam-0.1.0.dist-info/METADATA
skycam-0.1.0.dist-info/WHEEL
skycam-0.1.0.dist-info/licenses/LICENSE
skycam-0.1.0.dist-info/RECORD
