Metadata-Version: 2.4
Name: skycam
Version: 0.1.0
Summary: Camera-agnostic fisheye image projection library for ground-based sky observation
Author-email: Gabriel Jarry <gabriel.jarry@eurocontrol.int>
License: EUPL-1.2
License-File: LICENSE
Classifier: Development Status :: 3 - Alpha
Classifier: License :: OSI Approved :: European Union Public Licence 1.2 (EUPL 1.2)
Classifier: Programming Language :: Python :: 3.12
Classifier: Programming Language :: Python :: 3.13
Classifier: Typing :: Typed
Requires-Python: >=3.12
Requires-Dist: geographiclib>=2.0
Requires-Dist: loguru>=0.7.3
Requires-Dist: matplotlib>=3.10.8
Requires-Dist: numba>=0.60
Requires-Dist: numpy>=1.26
Requires-Dist: opencv-python>=4.9
Requires-Dist: pydantic-settings>=2.12.0
Requires-Dist: pydantic>=2.12.5
Requires-Dist: scikit-image>=0.26.0
Requires-Dist: scipy>=1.12
